{
  "strict": {
    "text-font-family": "Geometria",

    "text-heading-1-font-size": 36,
    "text-heading-1-font-weight": "800",

    "text-heading-2-font-weight": "900",

    "text-heading-3-font-weight": "800"
  },

  "components": {
    "Input": {
      "appearances": {
        "default": {
          "variantGroups": {
            "status": {
              "basic": {
                "borderColor": "border-basic-color-3",
                "backgroundColor": "background-basic-color-1"
              }
            }
          }
        }
      }
    },
    "Select": {
      "appearances": {
        "default": {
          "variantGroups": {
            "status": {
              "basic": {
                "borderColor": "border-basic-color-3",
                "backgroundColor": "background-basic-color-1"
              },
              "primary": {
                "borderColor": "color-primary-default",
                "backgroundColor": "background-basic-color-1"
              }
            }
          }
        }
      }
    },
    "Datepicker": {
      "appearances": {
        "default": {
          "variantGroups": {
            "status": {
              "basic": {
                "borderColor": "border-basic-color-3",
                "backgroundColor": "background-basic-color-1"
              }
            }
          }
        }
      }
    }
  }
}
